dimorphite_dl/__init__.py
dimorphite_dl/_version.py
dimorphite_dl/cli.py
dimorphite_dl/io.py
dimorphite_dl/mol.py
dimorphite_dl/neutralize.py
dimorphite_dl/protonate/__init__.py
dimorphite_dl/protonate/change.py
dimorphite_dl/protonate/data.py
dimorphite_dl/protonate/detect.py
dimorphite_dl/protonate/results.py
dimorphite_dl/protonate/run.py
dimorphite_dl/protonate/site.py
dimorphite_dl/smarts/site_substructures.smarts
dimorphite_dl-2.0.2.dist-info/licenses/LICENSE.md
dimorphite_dl-2.0.2.dist-info/METADATA
dimorphite_dl-2.0.2.dist-info/WHEEL
dimorphite_dl-2.0.2.dist-info/entry_points.txt
dimorphite_dl-2.0.2.dist-info/top_level.txt
dimorphite_dl-2.0.2.dist-info/RECORD
