Metadata-Version: 2.4
Name: dimorphite_dl
Version: 2.0.2
Summary: Adds hydrogen atoms to molecular representations as specified by pH
Author-email: "Durrant Lab @ Pitt" <durrantj@pitt.edu>
Maintainer-email: "Alex M. Maldonado" <alex.maldonado@pitt.edu>
License-Expression: Apache-2.0
Project-URL: Documentation, https://durrantlab.github.io/dimorphite_dl
Project-URL: Repository, https://github.com/durrantlab/dimorphite_dl
Project-URL: Issues, https://github.com/durrantlab/dimorphite_dl/issues
Project-URL: Changelog, https://github.com/durrantlab/dimorphite_dl/blob/main/CHANGELOG.md
Classifier: Development Status :: 5 - Production/Stable
Classifier: Intended Audience :: Developers
Classifier: Intended Audience :: Science/Research
Classifier: Natural Language :: English
Classifier: Programming Language :: Python
Classifier: Programming Language :: Python :: 3
Classifier: Programming Language :: Python :: 3.10
Classifier: Programming Language :: Python :: 3.11
Classifier: Programming Language :: Python :: 3.12
Classifier: Programming Language :: Python :: 3.13
Classifier: Topic :: Scientific/Engineering :: Chemistry
Requires-Python: >=3.10
License-File: LICENSE.md
Requires-Dist: loguru<0.8,>=0.7.2
Requires-Dist: rdkit<2026,>=2020.3.3
Dynamic: license-file
